ingest/__init__.py
ingest-0.0.1.dist-info/METADATA
ingest-0.0.1.dist-info/WHEEL
ingest-0.0.1.dist-info/entry_points.txt
ingest-0.0.1.dist-info/top_level.txt
ingest-0.0.1.dist-info/RECORD
